setup.py
my_state_machine/__init__.py
my_state_machine/example.py
my_state_machine/machine.py
my_state_machine/test.py
my_state_machine/visual.py
my_state_machine.egg-info/PKG-INFO
my_state_machine.egg-info/SOURCES.txt
my_state_machine.egg-info/dependency_links.txt
my_state_machine.egg-info/requires.txt
my_state_machine.egg-info/top_level.txt