Metadata-Version: 2.1
Name: my-state-machine
Version: 0.0.1
Summary: Simple State Machine
Author: Wenhan Zhang
License: MIT License
Platform: any
